{"Items":[{"Rarity":2,"Star":0,"MDPNDFFKNAC":0,"FAFGDGKLFEF":10,"StarRate":0,"RandRate":0,"BreakLevel":0,"BACPLGIJONA":[],"ENIECKNHKAN":[],"AGACEGHNPEM":[]},{"Rarity":2,"Star":1,"MDPNDFFKNAC":10,"FAFGDGKLFEF":20,"StarRate":8922,"RandRate":3000,"BreakLevel":1,"BACPLGIJONA":[],"ENIECKNHKAN":[],"AGACEGHNPEM":[]},{"Rarity":2,"Star":2,"MDPNDFFKNAC":20,"FAFGDGKLFEF":30,"StarRate":17844,"RandRate":6000,"BreakLevel":2,"BACPLGIJONA":[],"ENIECKNHKAN":[],"AGACEGHNPEM":[]},{"Rarity":2,"Star":3,"MDPNDFFKNAC":30,"FAFGDGKLFEF":40,"StarRate":26766,"RandRate":9000,"BreakLevel":3,"BACPLGIJONA":[],"ENIECKNHKAN":[],"AGACEGHNPEM":[]},{"Rarity":2,"Star":4,"MDPNDFFKNAC":40,"FAFGDGKLFEF":50,"StarRate":35688,"RandRate":12000,"BreakLevel":4,"BACPLGIJONA":[],"ENIECKNHKAN":[],"AGACEGHNPEM":[]},{"Rarity":2,"Star":5,"MDPNDFFKNAC":50,"FAFGDGKLFEF":60,"StarRate":44610,"RandRate":15000,"BreakLevel":5,"BACPLGIJONA":[],"ENIECKNHKAN":[],"AGACEGHNPEM":[]},{"Rarity":3,"Star":0,"MDPNDFFKNAC":0,"FAFGDGKLFEF":10,"StarRate":0,"RandRate":0,"BreakLevel":0,"BACPLGIJONA":[],"ENIECKNHKAN":[{"ItemID":301,"HMAMLIDMOLM":1}],"AGACEGHNPEM":[]},{"Rarity":3,"Star":1,"MDPNDFFKNAC":10,"FAFGDGKLFEF":20,"StarRate":8922,"RandRate":3000,"BreakLevel":1,"BACPLGIJONA":[],"ENIECKNHKAN":[{"ItemID":301,"HMAMLIDMOLM":1}],"AGACEGHNPEM":[]},{"Rarity":3,"Star":2,"MDPNDFFKNAC":20,"FAFGDGKLFEF":30,"StarRate":17844,"RandRate":6000,"BreakLevel":2,"BACPLGIJONA":[],"ENIECKNHKAN":[{"ItemID":301,"HMAMLIDMOLM":1}],"AGACEGHNPEM":[]},{"Rarity":3,"Star":3,"MDPNDFFKNAC":30,"FAFGDGKLFEF":40,"StarRate":26766,"RandRate":9000,"BreakLevel":3,"BACPLGIJONA":[],"ENIECKNHKAN":[{"ItemID":301,"HMAMLIDMOLM":1}],"AGACEGHNPEM":[]},{"Rarity":3,"Star":4,"MDPNDFFKNAC":40,"FAFGDGKLFEF":50,"StarRate":35688,"RandRate":12000,"BreakLevel":4,"BACPLGIJONA":[],"ENIECKNHKAN":[{"ItemID":301,"HMAMLIDMOLM":1}],"AGACEGHNPEM":[]},{"Rarity":3,"Star":5,"MDPNDFFKNAC":50,"FAFGDGKLFEF":60,"StarRate":44610,"RandRate":15000,"BreakLevel":5,"BACPLGIJONA":[],"ENIECKNHKAN":[{"ItemID":301,"HMAMLIDMOLM":1}],"AGACEGHNPEM":[]},{"Rarity":4,"Star":0,"MDPNDFFKNAC":0,"FAFGDGKLFEF":10,"StarRate":0,"RandRate":0,"BreakLevel":0,"BACPLGIJONA":[],"ENIECKNHKAN":[{"ItemID":301,"HMAMLIDMOLM":6}],"AGACEGHNPEM":[]},{"Rarity":4,"Star":1,"MDPNDFFKNAC":10,"FAFGDGKLFEF":20,"StarRate":8922,"RandRate":3000,"BreakLevel":1,"BACPLGIJONA":[],"ENIECKNHKAN":[{"ItemID":301,"HMAMLIDMOLM":6}],"AGACEGHNPEM":[]},{"Rarity":4,"Star":2,"MDPNDFFKNAC":20,"FAFGDGKLFEF":30,"StarRate":17844,"RandRate":6000,"BreakLevel":2,"BACPLGIJONA":[],"ENIECKNHKAN":[{"ItemID":301,"HMAMLIDMOLM":6}],"AGACEGHNPEM":[]},{"Rarity":4,"Star":3,"MDPNDFFKNAC":30,"FAFGDGKLFEF":40,"StarRate":26766,"RandRate":9000,"BreakLevel":3,"BACPLGIJONA":[],"ENIECKNHKAN":[{"ItemID":301,"HMAMLIDMOLM":6}],"AGACEGHNPEM":[]},{"Rarity":4,"Star":4,"MDPNDFFKNAC":40,"FAFGDGKLFEF":50,"StarRate":35688,"RandRate":12000,"BreakLevel":4,"BACPLGIJONA":[],"ENIECKNHKAN":[{"ItemID":301,"HMAMLIDMOLM":6}],"AGACEGHNPEM":[]},{"Rarity":4,"Star":5,"MDPNDFFKNAC":50,"FAFGDGKLFEF":60,"StarRate":44610,"RandRate":15000,"BreakLevel":5,"BACPLGIJONA":[],"ENIECKNHKAN":[{"ItemID":301,"HMAMLIDMOLM":6}],"AGACEGHNPEM":[]}]}